{
  "source_name": "أخصر المختصرات - ط ركائز.htm",
  "source_path_relative": "أخصر المختصرات - ط ركائز.htm",
  "status": "success",
  "source_format": "shamela_html",
  "composite_hash": "5cd4b5f13fd5212edfda759990856c067a707f8c03589fa72ad3130dbb41ff85",
  "file_hashes": {
    "أخصر المختصرات - ط ركائز.htm": "4e4e02cf2cd8244068294365cadb7f3d866c3529ec339eb582919a7a5a48a62c"
  },
  "extracted_metadata": {
    "is_multi_volume": false,
    "volume_count": 1,
    "has_muqaddima": false,
    "display_title": "أخصر المختصرات - ط ركائز",
    "author_short": "ابن بلبان الحنبلي",
    "shamela_category": "الفقه الحنبلي",
    "title_full": "أخصر المختصرات",
    "_field_source_title_full": "الكتاب",
    "author_name_raw": "محمد بن بدر الدين البلباني الدمشقي الخزرجي الحنبلي",
    "_field_source_author_name_raw": "المؤلف",
    "muhaqiq_name_raw": "د. عبد العزيز بن عدنان العيدان، د. أنس بن عادل اليتامى",
    "_field_source_muhaqiq_name_raw": "المحقق",
    "publisher": "دار ركائز للنشر والتوزيع - الكويت، دار الصميعي للنشر والتوزيع، الرياض - المملكة العربية السعودية",
    "_field_source_publisher": "الناشر",
    "edition_raw": "الأولى، 1438 هـ - 2017 م",
    "_field_source_edition_raw": "الطبعة",
    "page_count_raw": "346",
    "_field_source_page_count_raw": "عدد الصفحات",
    "preparer": "ركائز للنشر والتوزيع؛ جزاهم الله خيرا",
    "_field_source_preparer": "أهداه للشاملة",
    "shamela_publish_date": "25 جُمادَى الآخرة 1440",
    "_field_source_shamela_publish_date": "تاريخ النشر بالشاملة",
    "_physical_page_count": 346,
    "edition_number": 1,
    "edition_year_hijri": 1438,
    "edition_year_miladi": 2017,
    "body_page_count": 336,
    "page_count": 336,
    "text_sample": "كتاب أخصر المختصرات\nحقوق الطبع محفوظةلدار ركائز للنشر والتوزيعالطبعة الأولى1438 هـ - 2017 م دار الطميعي للنشر والتوزيع\nكتاب أخصر المختصرات تأليف الإماممحمد بن بدر الدين البلباني الدمشقي الخزرجي الحنبلي قوبل على أربع نسخ بخط المؤلفتحقيقد. عبد العزيز بن عدنان العيداند. أنس بن عادل اليتامى\nبسم الله الرحمن الرحيم\nبسم الله الرحمن الرحيموبه نستعينإنَّ الحمد لله نحمده ونستعينه ونستغفره، ونعوذ بالله من شرور أنفسنا ومن سيئات أعمالنا، من يهده الله فلا مضل له، ومن يضلل فلا هادي له، ونشهد ألا إله إلا الله وأن محمداً عبده ورسوله، صلى الله عليه وعلى آله وصحبه وسلم تسليماً كثيراً.أما بعد؛فإنَّ من البركة والتوفيق التي تَغشى العبدَ، ما يجعله الله من القبول لعلمه، والبركة في تعليمه، فإن العبد قد يكتب كتاباً أو يقول كلمةً فلا يرى أثرها في وقتها بل ولا في زمانه، ثم يبارك الله في ذلك أيما بركة، وذلك فضل الله يؤتيه من يشاء، والله ذو الفضل العظيم.وإنَّ من ذلك -والله أعلم- ما جعله الله تعالى لكتاب (أَخْصَرِ المُخْتَصَرَاتِ) من القبول والإقبال من المعلمين والمتعلمين لا سِيمَّا في زماننا هذا، حتى صار جُلُّ المبتدئين والمتعلمين على فقه مذهب الحنابلة يَنصبُّ اهتمامهم وعنايتهم على هذا المختصر.وهذا - وإن كان بفضل الله ومنته على كاتبه ابن بلبان - إلا أن صِغَر حجم هذا المختصر، وسهولةَ عِبارته، ووضوحَ معانيه، واحتواءَه\nعلى جُلِّ المسائل الكبار، واقتصارَه على المعتمَد عند المتأخرين؛ جعله محَطَّ ذلك الاهتمام من أهل هذا الزمان.ولأجل هذا قمنا بوضع دلائل وإشارات على هذا المختصر في كتابٍ سميناه: (الدَّلَائِلَ وَالإِشَارَاتِ عَلَى أَخْصَرِ المُخْتَصَرَاتِ).ثم رأينا بعد ذلك: أن هذا المختصر بحاجة إلى أن يكون بين يدي المتفقِّه - وخاصة المبتدئ - بأسلوبٍ تكون المسائل فيه مرتبة، بحيث يعرف الناظر فيه أمَّات تلك المسائل، وفروعها الملحقة بها، والأنواع والتقاسيم الواردة عليها؛ حتى تنتظم مسائل الباب في ذهنه وتكون في نسق متسق، فقمنا بالرجوع إلى نسخه الخطية وانتقاء أفضلها، وصغناه صياغة تتوافق مع ما تقدم ذكره، والله الموفق والهادي إلى سبيل العلم والرشاد.ولا يخفى أن ثَمَّ مواطن في مثل هذا العمل خاصة تختلف فيها أنظار النظار، إلا أن ذلك لا يُغلق باب تسهيل العلم على المتفقهين، وتقريبه للطالبين، ولا يزال هذا التسهيل والتقري",
    "_quality_issues": [],
    "format_specific_metadata": {
      "shamela_category": "الفقه الحنبلي",
      "shamela_publish_date": "25 جُمادَى الآخرة 1440",
      "edition_raw": "الأولى، 1438 هـ - 2017 م",
      "page_count_raw": "346",
      "author_short": "ابن بلبان الحنبلي",
      "preparer": "ركائز للنشر والتوزيع؛ جزاهم الله خيرا",
      "physical_page_count": 346
    }
  },
  "quality_issues": [],
  "processing_time_ms": 8.3,
  "error": null
}