{
  "source_name": "أصول العقيدة - عبد الرحيم السلمي",
  "source_path_relative": "أصول العقيدة - عبد الرحيم السلمي",
  "status": "success",
  "source_format": "shamela_html",
  "composite_hash": "b6e2a1f4d3a5c7a29494a5486135b4ea1a9ee2586c2ba2de8536658ddcdb5aac",
  "file_hashes": {
    "001.htm": "9a5f4695d77eabd1fa3ca27059b520ea7ad3f0ced5cff7f1ac19198654636b1c",
    "002.htm": "30fa82ed9503b3836b3aa3c8468dbae5f9443ca0fcd4ff9f517a0ab0069761f3",
    "003.htm": "d6489e05d363e66a5e53c99eac173b6ad53f49a8118437f89fac83e0f8c05dff",
    "004.htm": "51dcc15c757e2609ab77cdf596c48813c0b943bc059cd790626ae7e9d0546859",
    "005.htm": "bfac45984313c749f2479865d982170a3b219f782113189ff21a9f93082b5089",
    "006.htm": "64355273a1678f321dedd4c38938c9c0ff62c99533762584d0d8b532e8a6b75b",
    "007.htm": "22d6089f85fcb7206456c018598373e11b49963d27a649763793636a2043bb58",
    "008.htm": "4ad5137f836aa26688e6baa58298b3e2a29319efc403aca4b2d8e4186e206452",
    "009.htm": "4e293f5a3e9852c1f001a10dc5edb5cbac1ea8b37c61327eaa45b2b4fb00f095"
  },
  "extracted_metadata": {
    "is_multi_volume": true,
    "volume_count": 9,
    "has_muqaddima": false,
    "display_title": "أصول العقيدة - عبد الرحيم السلمي",
    "author_short": "عبد الرحيم السلمي",
    "shamela_category": "العقيدة",
    "title_full": "أصول العقيدة",
    "_field_source_title_full": "الكتاب",
    "author_name_raw": "عبد الرحيم بن صمايل العلياني السلمي",
    "_field_source_author_name_raw": "المؤلف",
    "source_note": "دروس صوتية قام بتفريغها موقع الشبكة الإسلامية",
    "_field_source_source_note": "مصدر الكتاب",
    "_extra_card_fields": {
      "http": "//www.islamweb.net"
    },
    "shamela_publish_date": "12 شعبان 1432",
    "_field_source_shamela_publish_date": "تاريخ النشر بالشاملة",
    "body_page_count": 22,
    "page_count": 22,
    "text_sample": "‌‌أصول العقيدة [1]للعلم آداب ينبغي على طالب العلم معرفتها والتأدب بها، أهمها إخلاص النية لله تعالى، وجملة من الآداب المهمة، وعلم العقيدة أول العلوم في الحاجة إلى تلك الآداب، وإلى الإلمام بمسائله، لا سيما مسائل التوحيد العظيمة.\n‌‌مقدمة في آداب طالب العلمالحمد لله، والصلاة والسلام على رسول الله، وعلى آله وصحبه، وسلم تسليماً كثيراً إلى يوم الدين.أما بعد: فهذا هو الدرس الأول من دروس أصول العقيدة، وسوف يكون الكلام في هذا الدرس حول ثلاثة أمور: الأمر الأول: مقدمة في آداب طالب العلم.الأمر الثاني: المنهج الذي سنتبعه في هذا الدرس بإذن الله تعالى.الأمر الثالث: الكلام في المسألة الأولى من مسائل أصول العقيدة وهي مسألة: فطرية التوحيد.لقد كان السلف الصالح رضوان الله عليهم أجمعين يعتنون عناية كبيرة بآداب طالب العلم، وآداب طالب العلم مذكورة في السنة النبوية، وكان النبي صلى الله عليه وسلم يعلم الصحابة الأدب كما يعلمهم العلم أيضاً، وحديث جبريل الطويل الذي سأل فيه النبي صلى الله عليه وسلم عن الإسلام والإيمان والإحسان وعن أشراط الساعة تعلم الصحابة رضوان الله عليهم فيه الأدب في السؤال والاستماع والجلوس بين يدي المعلم، ولهذا جاء في آخر الحديث أن النبي صلى الله عليه وسلم قال: (هذا جبريل جاءكم يعلمكم دينكم).فالأدب في طلب العلم من الدين، ولهذا ذكر النبي صلى الله عليه وسلم في حديث طويل كما في صحيح البخاري قصة موسى عليه السلام مع الخضر، وهذا الحديث فيه كثير من الأحكام والآداب، ومن أبرزها أدب طالب العلم.يقول عبد الله بن المبارك: طلبت الأدب ثلاثين سنة، وطلبت العلم عشرين سنة، وكانوا يطلبون الأدب قبل العلم.ويقول أيضاً رحمه الله تعالى: يكاد يكون الأدب ثلثي العلم.وهناك آداب كثيرة لطالب العلم يمكن أن نتحدث عن أبرزها، منها:\n‌‌إخلاص النية لله عز وجلالأمر الأول: إخلاص النية لله سبحانه وتعالى، فإن هذا العلم من الدين، والدين من شروطه الأساسية التي تجعله مقبولاً عند الله ومباركاً فيه أن يكون خالصاً لوجهه تعالى، يقول الله عز وجل: {وَمَا أُمِرُوا إِلَّا لِيَعْبُدُوا اللَّهَ مُخْلِصِينَ لَهُ الدِّينَ} [البينة:5]، وقال تعالى: {أَلا لِلَّهِ الدِّينُ الْخَالِصُ} [الزمر:3].وجاء في الحديث عن النبي صلى الله عليه وسلم أنه قال: (أول من تسعر بهم النار يوم القيامة ثلاثة: -وذكر منهم- قارئ القرآن)، وفي بعض ألفاظ الحديث: ",
    "_quality_issues": [],
    "format_specific_metadata": {
      "shamela_category": "العقيدة",
      "shamela_publish_date": "12 شعبان 1432",
      "source_note": "دروس صوتية قام بتفريغها موقع الشبكة الإسلامية",
      "author_short": "عبد الرحيم السلمي",
      "extra_card_fields": {
        "http": "//www.islamweb.net"
      }
    }
  },
  "quality_issues": [],
  "processing_time_ms": 8.8,
  "error": null
}