{
  "source_name": "الإجماع في الشريعة الإسلامية.htm",
  "source_path_relative": "الإجماع في الشريعة الإسلامية.htm",
  "status": "success",
  "source_format": "shamela_html",
  "composite_hash": "a269bb47c03fe45dd553d311e75339a080044261c77cccf651b81e1f6fa065e9",
  "file_hashes": {
    "الإجماع في الشريعة الإسلامية.htm": "dbcf5fdd20d26bf27e0bd63f0f530b967cd508189779cae6abea71af81498f87"
  },
  "extracted_metadata": {
    "is_multi_volume": false,
    "volume_count": 1,
    "has_muqaddima": false,
    "display_title": "الإجماع في الشريعة الإسلامية",
    "author_short": "رشدي عليان",
    "shamela_category": "أصول الفقه",
    "title_full": "الإجماع في الشريعة الإسلامية",
    "_field_source_title_full": "الكتاب",
    "author_name_raw": "رشدي عليان",
    "_field_source_author_name_raw": "المؤلف",
    "publisher": "الجامعة الإسلامية",
    "_field_source_publisher": "الناشر",
    "edition_raw": "السنة العاشرة، العدد الأول، جمادى الأخرة 1397هـ مايو - يونية 1977 م",
    "_field_source_edition_raw": "الطبعة",
    "page_count_raw": "82",
    "_field_source_page_count_raw": "عدد الصفحات",
    "shamela_publish_date": "8 ذو الحجة 1431",
    "_field_source_shamela_publish_date": "تاريخ النشر بالشاملة",
    "_physical_page_count": 82,
    "edition_number": 1,
    "edition_year_hijri": 1397,
    "edition_year_miladi": 1977,
    "body_page_count": 25,
    "page_count": 25,
    "text_sample": "‌‌مدخل…الإجماع في الشريعة الإسلاميةلفضيلة الدكتور رشدي عليان الأستاذ المشارك بكلية الدعوة وأصول الدين في الجامعة الإسلاميةالإجماع من البحوث النافعة والهامة في علم أصول الفقه، استأثر بعناية خاصة من أعلام الأمة ومفكريها لأنه الدليل الذي يلي النصوص في القوة والاحتجاج. فإذا ما عرضت للمجتهد حادثة، وأراد معرفة رأي الشريعة فيها عرضها أولا على كتاب الله _ تعالى _ عمدة الشريعة وكليّها، فإذا لم يجد بغيته مال إلى سنة رسول الله _ عليه الصلاة والسلام _ باعتبارها المصدر الثاني للشريعة، فإن أعياه البحث ولم يجد ضالته فيها نظر هل اتفق السابقون على حكم لها؟ فإن وجد عمل به وأفتى بموجبه وهو مطمئن البال، فالأمة لا تجتمع على الخطأ والضلالة كما أخبر بذلك الصادق الأمين _ عليه أفضل الصلاة والتسليم _ وإذا لم يسعفه الإجماع لجأ إلى أدلة أخرى معروفة في أصول الفقه كالقياس والاستصحاب والمصلحة..حدث ميمون بن مهران فقال: \"كان أبو بكر الصديق إذا ورد عليه خصم نظر في كتاب الله فإن وجد قضى به، وإلا نظر في سنة رسول الله فإن وجد فيها ما يقضي به قضى به، فإن أعياه ذلك سأل الناس وجمع رؤساءهم واستشارهم، فإن اجتمع رأيهم على شيء قضى به، وكان عمر يفعل ذلك، فإن أعياه أن يجد ذلك في الكتاب والسنة، سأل هل كان أبو بكر قضى فيه بقضاء؟ وإلا جمع الناس واستشارهم فإذا اجتمع رأيهم على شيء قضى به.وبعد فلمّا كان الإجماع يتكوّن من ركنين:(1) مجمع عليه.(2) ومجمعين وهم أهل الإجماع فقد جاءت هذه الدراسة في مبحثين: _ الأول في المجمع عليه. وفحواه تعريف الإجماع، سنده، حجيته، أنواعه، مخالفة حكمه.\nوالثاني في المجمعين ((أهل الإجماع)) 1 الصحابة، الخلفاء الأربعة، أهل البيت، أهل المدينة، أهل الكوفة والبصرة، جماعة المجتهدين في أي عصره.\n‌‌المبحث الأول: في المجمع عليه‌‌تعريف الإجماع في اللغة والاصطلاح…المبحث الأول: في المجمع عليه1_ تعريف الإجماع في اللغة وفي اصطلاح الأصوليين.أ_ الإجماع في اللغة: _الإجماع من الألفاظ المشتركة في وضع اللغة بين معنيين: _الأول: العزم. يقال: ((أجمع فلان على كذا)) إذا عزم عليه، وجاء في الحديث \"لا صيام لمن لم يجمع الصيام من الليل\"2 أي لم يعزم الصيام من الليل وورد في الكتاب الكريم {فَأَجْمِعُوا أَمْرَكُمْ} 3 أي اعزموا. والإجماع بهذا المعنى يصدر عن الواحد كما في المثال الأول، وكما جاء في الحديث، ويصدر عن الجمع كما في ال",
    "_quality_issues": [],
    "format_specific_metadata": {
      "shamela_category": "أصول الفقه",
      "shamela_publish_date": "8 ذو الحجة 1431",
      "edition_raw": "السنة العاشرة، العدد الأول، جمادى الأخرة 1397هـ مايو - يونية 1977 م",
      "page_count_raw": "82",
      "author_short": "رشدي عليان",
      "physical_page_count": 82
    }
  },
  "quality_issues": [],
  "processing_time_ms": 1.4,
  "error": null
}