{
  "source_name": "السيرة النبوية - دروس وعبر.htm",
  "source_path_relative": "السيرة النبوية - دروس وعبر.htm",
  "status": "success",
  "source_format": "shamela_html",
  "composite_hash": "ed5a512279cf256cccba09dcc048946f6b14d70e7626b581a9b98cce6aba1f62",
  "file_hashes": {
    "السيرة النبوية - دروس وعبر.htm": "cdbd67ed08922ef0f47e1832a781815386a01acbe4637ce738b66f12a3135434"
  },
  "extracted_metadata": {
    "is_multi_volume": false,
    "volume_count": 1,
    "has_muqaddima": false,
    "display_title": "السيرة النبوية - دروس وعبر",
    "author_short": "مصطفى السباعي",
    "shamela_category": "السيرة النبوية",
    "title_full": "السيرة النبوية - دروس وعبر",
    "_field_source_title_full": "الكتاب",
    "author_name_raw": "د مصطفى السباعي (ت 1384 هـ)",
    "_field_source_author_name_raw": "المؤلف",
    "publisher": "المكتب الإسلامي، (بيروت - دمشق)",
    "_field_source_publisher": "الناشر",
    "edition_raw": "الثامنة، 1405 هـ - 1985 م",
    "_field_source_edition_raw": "الطبعة",
    "page_count_raw": "172",
    "_field_source_page_count_raw": "عدد الصفحات",
    "shamela_publish_date": "11 شوّال 1432",
    "_field_source_shamela_publish_date": "تاريخ النشر بالشاملة",
    "author_death_hijri": 1384,
    "author_name_clean": "د مصطفى السباعي",
    "_physical_page_count": 172,
    "edition_number": 8,
    "edition_year_hijri": 1405,
    "edition_year_miladi": 1985,
    "body_page_count": 156,
    "page_count": 156,
    "text_sample": "‌‌مقدمة المؤلفالحمد لله الذي أرسل رسوله بالبينات والهدى، ليخرجوا الناس من الظلمات إلى النور، ويهدوهم إلىى صراط العزيز الحميد.والصلاة والسلام على أفضل رسله، وأشرف دعاته، سيدنا محمد صلى الله عليه وسلم الذي ختم الله به رسله، فجعل سيرته قدوة لكل مؤمن في جميع شؤون الحياة صغيرها وكبيرها، وختم بدينه الشرائع، فجعل رسالته أكمل الرسالات وأوفاها بحاجات الناس في مختلف بيئاتهم وعصورهم، صلى الله وسلم عليه وعلى أصحابه الهداة البررة الذين علم الله فيهم سلامة الفطرة، وصدق العقيدة، وعظيم التضحية، فشرفهم بحمل رسالة الإسلام إلى أمم الأرض، فأراقوا في سبيلها دماءهم، وفارقوا من أجلها ديارهم، حتى أدوا الأمانة، وبلغوا الرسالة، ونصحوا لله ورسوله، فكان لهم فضل على الإنسانية لا يعرف مداها، ودين في عنق كل مسلم حتى يرث الله الأرض ومن عليها، رضوان الله عليهم وعلى من أحبهم وحمل لواء الدعوة إلى الله من بعدهم حتى يوم الدين.وبعد فهذه مذكرات كتبتها على عجل وشدة من المرض بعد أن ألقيتها محاضرة مفصلة على طلاب السنة الأولى في كلية الشريعة توخيت فيها أن أبرز أوضح مظاهر الأسوة في سيرة الرسول الكريم صلى\nالله عليه وسلم، مما ينبغي على كل مسلم وداعية إلى الله عز وجل، وعالم بالشريعة، وحامل لفقهها، أن يتدبره ويجعله نصب عينيه، ليكون له شرف الاقتداء برسوله صلى الله عليه وسلم، وليفتح أمامه باب النجاح في دعوته بين الناس، وباب القبول والرضى من الله جل شأنه، وليكتب له شرف الخلود مع رسوله صلى الله عليه وسلم في جنات النعيم، فإن الله تعالى يقول: {وَمَن يُطِعِ اللهَ وَرَسُولَهُ يُدْخِلْهُ جَنَّاتٍ تَجْرِي مِن تَحْتِهَا الأَنْهَارُ خَالِدِينَ فِيهَا وَذَلِكَ الْفَوْزُ الْعَظِيمُ} [النساء: 13].هذا وقد جعلت البحث وفق المنهج التالي:أ- مقدمة وتشتمل على بحثين:1 - في ميزة السيرة النبوية والفائدة من دراستها.2 - في مصادر السيرة النبوية ومراجعها الصحيحة.ب- في فقه سيرته صلى الله عليه وسلم ويشتمل على عشرة فصول.الفصل الأول- في حياته صلى الله عليه وسلم قبل البعثة.الفصل الثاني- في حياته بعد البعثة إلى الهجرة إلى الحبشة.الفصل الثالث- في حياته بعد هجرة الحبشة إلى الهجرة للمدينة.الفصل الرابع- في هجرته حتى استقراره بالمدينة.الفصل الخامس- في معاركه الحربية منذ غزوة بدر حتى فتح مكة.الفصل السادس- في انتشار الإسلام في جزيرة العرب بعد الفتح.الفصل",
    "_quality_issues": [],
    "format_specific_metadata": {
      "shamela_category": "السيرة النبوية",
      "shamela_publish_date": "11 شوّال 1432",
      "edition_raw": "الثامنة، 1405 هـ - 1985 م",
      "page_count_raw": "172",
      "author_short": "مصطفى السباعي",
      "physical_page_count": 172
    }
  },
  "quality_issues": [],
  "processing_time_ms": 5.0,
  "error": null
}