{
  "source_name": "الإمام مسلم وصحيحه.htm",
  "source_path_relative": "الإمام مسلم وصحيحه.htm",
  "status": "success",
  "source_format": "shamela_html",
  "composite_hash": "b2e958afb33a0afdd2c1d98433cbe8e46d139da87977f3c103e3930cb197112e",
  "file_hashes": {
    "الإمام مسلم وصحيحه.htm": "37a1f497a698eaa26bce9a8a03b1f26cf279ff2126584f0ab25d84ff7f59e557"
  },
  "extracted_metadata": {
    "is_multi_volume": false,
    "volume_count": 1,
    "has_muqaddima": false,
    "display_title": "الإمام مسلم وصحيحه",
    "author_short": "عبد المحسن العباد",
    "shamela_category": "علوم الحديث",
    "title_full": "الإمام مسلم وصحيحه",
    "_field_source_title_full": "الكتاب",
    "author_name_raw": "عبد المحسن بن حمد بن عبد المحسن بن عبد الله بن حمد العباد البدر",
    "_field_source_author_name_raw": "المؤلف",
    "publisher": "الجامعة الإسلامية، المدينة المنورة",
    "_field_source_publisher": "الناشر",
    "edition_raw": "السنة الثالثة - العدد الأول، 1390هـ/1970م",
    "_field_source_edition_raw": "الطبعة",
    "page_count_raw": "50",
    "_field_source_page_count_raw": "عدد الصفحات",
    "shamela_publish_date": "8 ذو الحجة 1431",
    "_field_source_shamela_publish_date": "تاريخ النشر بالشاملة",
    "_physical_page_count": 50,
    "edition_number": 1,
    "edition_year_hijri": 1390,
    "edition_year_miladi": 1970,
    "body_page_count": 40,
    "page_count": 40,
    "text_sample": "‌‌الامام مسلم‌‌نسبه…الإمام مسلم وصحيحهبقلم الشيخ: عبد المحسن العباد المدرس بكلية الشريعة بالجامعة الإسلاميةنسبه:هو الإمام أبو الحسن مسلم بن الحجاج بن مسلم القشيري نسبا النيسابوري وطنا، قال ابن الأثير في اللباب في تهذيب الأنساب: القشيري بضم القاف وفتح الشين وسكون الياء تحتها نقطتان وفي آخرها راء، هذه النسبة إلى قشير بن كعب بن ربيعة بن عامر بن صعصعة قبيلة كبيرة ينسب إليها كثير من العلماء فذكر جماعة من هؤلاء ومنهم الإمام مسلم، ونسبة الإمام مسلم هذه نسبة أصل بخلاف الإمام البخاري فإن نسبته إلى الجعفيين نسبة ولاء ولهذا لما ذكر الإمام أبو عمر بن الصلاح في كتابه علوم الحديث أن أول من ألف في الصحيح الإمام البخاري ثم الإمام مسلم قال: \"أول من صنف الصحيح البخاري أبو عبد الله محمد بن إسماعيل الجعفي مولاهم وتلاه أبو الحسين مسلم بن الحجاج النيسابوري القشيري من أنفسهم\".\n‌‌ولادته:ولد الإمام مسلم سنة أربع ومائتين كما في خلاصة تهذيب الكمال للخزرجي وتهذيب التهذيب وتقريبه للحافظ ابن حجر العسقلاني، وكذا في البداية والنهاية لابن كثير، قال بعد أن ذكر وفاته سنة إحدى وستين ومائتين: وكان مولده في السنة التي توفي فيها الشافعي وهي سنة أبع ومائتين فكان عمره سبعا وخمسين سنة رحمه الله تعالى، ونقل ابن خلكان في كتابه وفيات الأعيان عن كتاب (علماء الأمصار) لأبي عبد الله النيسابوري الحاكم أن مسلما توفي بنيسابور لخمس بقين من شهر رجب الفرد سنة إحدى وستين ومائتين وهو ابن خمسة وخمسين سنة ثم قال: فتكون ولادته في سنة ست ومائتين.\n‌‌رحلته في طلب العلم وسماعه الحديث:بدأ سماع الحديث سنة ثماني عشرة ومائتين كما في تذكرة الحفاظ للذهبي، وقد رحل لطلبه إلى العراق والحجاز والشام ومصر، وروى عن جماعة كثيرين أذكر فيما يلي عشرة من الذين أكثر من السماع منهم والرواية عنهم في صحيحه مع بيان عدد ما رواه عن كل منهم كما نقل ذلك الحافظ ابن حجر في تراجمهم في كتابه تهذيب التهذيب:1- أبو بكر ابن أبي شيبة: 1540 حديثا.2- أبو خيثمة زهير بن حرب: 1281 حديثا.3- محمد بن المثني الملقب الزمن: 772 حديثا.4- قتيبة بن سعيد: 668 حديثا.5- محمد بن عبد الله بن نمير: 573 حديثا.6- أبو كريب محمد بن العلاء ابن كريب: 556 حديثا.7- محمد بن بشار الملقب بندارا: 460 حديثا.8- محمد بن رافع النيسابوري: 362 حديثا.9- محمد بن حاتم الملقب السمين: 300 حديثا.10- علي بن ",
    "_quality_issues": [],
    "format_specific_metadata": {
      "shamela_category": "علوم الحديث",
      "shamela_publish_date": "8 ذو الحجة 1431",
      "edition_raw": "السنة الثالثة - العدد الأول، 1390هـ/1970م",
      "page_count_raw": "50",
      "author_short": "عبد المحسن العباد",
      "physical_page_count": 50
    }
  },
  "quality_issues": [],
  "processing_time_ms": 1.2,
  "error": null
}