{
  "source_name": "الطريق إلى الولد الصالح.htm",
  "source_path_relative": "الطريق إلى الولد الصالح.htm",
  "status": "success",
  "source_format": "shamela_html",
  "composite_hash": "9f2dd0d12c8ad8c46beb51e54cb9f7d29380170a798637778453ac3887b6f1f3",
  "file_hashes": {
    "الطريق إلى الولد الصالح.htm": "cb3da5cc42aec5ae7637d912804f588a2ebf17a611839125673861bb3e1098f1"
  },
  "extracted_metadata": {
    "is_multi_volume": false,
    "volume_count": 1,
    "has_muqaddima": false,
    "display_title": "الطريق إلى الولد الصالح",
    "author_short": "وحيد عبد السلام بالي",
    "shamela_category": "الرقائق والآداب والأذكار",
    "title_full": "الطريق إلى الولد الصالح",
    "_field_source_title_full": "الكتاب",
    "author_name_raw": "وحيد بن عبد السلام بالي",
    "_field_source_author_name_raw": "المؤلف",
    "publisher": "دار الضياء للنشر والتوزيع - السعودية",
    "_field_source_publisher": "الناشر",
    "page_count_raw": "57",
    "_field_source_page_count_raw": "عدد الصفحات",
    "shamela_publish_date": "3 محرم 1433",
    "_field_source_shamela_publish_date": "تاريخ النشر بالشاملة",
    "_physical_page_count": 57,
    "body_page_count": 52,
    "page_count": 52,
    "text_sample": "الطريق إلى الولد الصالحتأليفوحيد عبد السلام بالي\n‌‌مقدمةإن الحمد لله نحمده ونستعينه ونستهديه ونستغفره، ونعوذ بالله من شرور أنفسنا ومن سيئات أعمالنا من يهده الله فلا مضل له ومن يضلل فلا هادي له وأشهد أن لا إله إلا الله وحده لا شريك له وأشهد أن محمداً عبده ورسوله. وبعد فإنه لا مخرج لنا من الأزمة التي نحن فيها إلا بالعودة إلى كتاب الله وسنة رسول الله صلى الله عليه وسلم قولاً وعملاً وتطبيقاً، وتحكيم الكتاب والسنة في كل أمورنا صغيرها كبيرها، عظيمها وحقيرها، ثم تنشئة أولادنا على ذلك وغرس حب الله والرسول في قلوبهم، وتعويدهم منذ الصغر على التضحية من أجل\nهذا الدين والعمل لرفعة هذا الدين وبذل الغالي والرخيص في سبيل إعلاء هذا الدين. وقتها سيعود جيل خالد بن الوليد، وطلحة بن عبيد الله وسعد بن أبي وقاص، وقتها سيسود المسلمون العالم كما ساده أجدادهم من قبل {وَيَوْمَئِذٍ يَفْرَحُ الْمُؤْمِنُونَ، بِنَصْرِ اللَّهِ} [الروم: 4، 5]. من أجل ذلك كتبت هذه الكلمات سائلا المولى تبارك وتعالى أن ينفع بها في حياتي وبعد مماتي إنه أكرم مسؤول، وصلى اللهم وسلم على عبدك ورسولك محمد وعلى آله وصحبه أجمعين. وكتبه وحيد ابن عبد السلام باليمدينة الرسول صلى الله عليه وسلمفي 22/ 1/ 1410هـ\nبسم الله الرحمن الرحيم الولد الصالح هو خير كنز يتركه المسلم من بعده، فهو نافع لأبويه في حياتهما وبعد موتهما. ولذلك يقول النبي صلى الله عليه وسلم: ((إذا مات العبد انقطع عمله إلا من ثلاث: صدقة جارية أو علم ينتفع به، أو ولد صالح يدعو له)). بل إن الذرية الصالحة يجمع شملها من آبائها الصالحين في الجنة {وَالَّذِينَ آمَنُوا وَاتَّبَعَتْهُمْ ذُرِّيَّتُهُمْ بِإِيمَانٍ أَلْحَقْنَا بِهِمْ ذُرِّيَّتَهُمْ وَمَا أَلَتْنَاهُمْ مِنْ عَمَلِهِمْ مِنْ شَيْءٍ} [الطور: 21]، فعلى المسلم أن يأخذ بالأسباب لنيل الولد الصالح وهذه الأسباب نجملها فيما يأتي:\n‌‌1 - اختيار الأم:على المسلم أن يختار لأبنائه الأم المسلمة التي تعرف حق ربها، وحق زوجها، وحق ولدها، والأم التي تعرف رسالتها في الحياة، الأم التي تعرف موقعها في هذه المحن، الأم التي تغار على دينها، وعلى سنة نبيها صلى الله عليه وسلم. وذلك لأن الأم هي المصنع الذي سيصنع فيه أبناؤك وهي المدرسة التي سيتخرجون منها فإن كانت صالحة أرضعتهم الصلاح والتقوى، وإن كانت غير ذلك فكذلك. وصدق الشاعر:الأم مدرسة إذا أعد",
    "_quality_issues": [],
    "format_specific_metadata": {
      "shamela_category": "الرقائق والآداب والأذكار",
      "shamela_publish_date": "3 محرم 1433",
      "page_count_raw": "57",
      "author_short": "وحيد عبد السلام بالي",
      "physical_page_count": 57
    }
  },
  "quality_issues": [],
  "processing_time_ms": 1.6,
  "error": null
}