{
  "source_name": "الثورة البائسة.htm",
  "source_path_relative": "الثورة البائسة.htm",
  "status": "success",
  "source_format": "shamela_html",
  "composite_hash": "715d632ab1d85b4331991fc13dff96b0e5149efca1b87440ebd9f79233ffd3eb",
  "file_hashes": {
    "الثورة البائسة.htm": "cce0543eba5a701d5ce0fa6d010e045742dd2f8e59352d386a5e9ccd21d149b9"
  },
  "extracted_metadata": {
    "is_multi_volume": false,
    "volume_count": 1,
    "has_muqaddima": false,
    "display_title": "الثورة البائسة",
    "author_short": "موسى الموسوي",
    "shamela_category": "العقيدة",
    "title_full": "الثورة البائسة",
    "_field_source_title_full": "الكتاب",
    "author_name_raw": "د موسى الموسوي",
    "_field_source_author_name_raw": "المؤلف",
    "volume_count_raw": "1",
    "_field_source_volume_count_raw": "عدد الأجزاء",
    "shamela_publish_date": "26 ذو القعدة 1432",
    "_field_source_shamela_publish_date": "تاريخ النشر بالشاملة",
    "_metadata_volume_count": 1,
    "body_page_count": 216,
    "page_count": 216,
    "text_sample": "الثورة البائسةتأليف: الدكتور الشيعي موسى الموسوي\nبسم الله الرحمن الرحيم(رَبِّ اشْرَحْ لِي صَدْرِي * وَيَسِّرْ لِي أَمْرِي*وَاحْلُلْ عُقْدَةً مِنْ لِسَانِي * يَفْقَهُوا قَوْلِي) [طه:25 - 28]\n‌‌الإهداءيا رسول الله يا نبي الرحمة، لقد تضافرت الفئة الضالة المضلة الحاكمة باسمك على رقاب المسلمين في تشويه رسالتك ونقاء صورتك، فصورت شريعتك السمحة السهلاء الرحماء، شريعة القتل والتعذيب والدمار والفناء.وبذلت هذه العصابة بكل ما أوتيت من جهد وقوة وسلطان ومكر ودهاء أن تتخذ من اسمك العظيم ورسالتك التي كانت للناس نورا وكرامة ومزيدا، ذريعة لظلم العباد وخراب البلاد فجلس كبيرهم الذي علمهم السحر على صرح من الجماجم البشرية باسم الإسلام وحوله تجري انهار من الدماء والدموع.لقد قتلوا العباد المخلصين باسم الله، وعذبوا خاصة الأولياء باسم الله وسلبوا ونهبوا أموال المؤمنين باسم الله، واقترفوا كل جرم وجريرة ونكر وفساد باسم الله، ولو أن يا رسول الله ويا إمام الهدى قدر لهذه العصابة النجاح والتوفيق في مآربها فلن يعبد الله في تلك الأرض ولن يذكر فيها اسمك، فها أنا قد نهضت لكي أردهم على أعقابهم واكشف سرهم وافضح أمرهم واجعلهم شذرا مذرا واستمد من الله الحول والقوة والعون والتوفيق والنجاح المكلل بالنصر المبين.واليك يا رسول الله اهدي ما خطته يميني في هذه الصحائف عسى أن يكون فيها رضا الله ورضاك وتنفعني في يوم لا ينفع فيه مال ولا بنون إلا من أتى الله بقلب سليم.\n‌‌المقدمةلأول مرة يحدث مثل هذا الانحدار الخطير في تاريخ الإسلام، حيث تقوم شرذمة باسم الدين لتملأ العالم فسادا ونكرا وشرا لم يحدث له نظير من قبل ولا من بعد. وان اخطر ما يكمن في هذا الفساد والشر هو أن هذه العصابة حاولت بكل ما أوتيت من قوة وسلطان أن تقلب الموازين الثابتة للأخلاق وتغير الحدود الرصينة بين الخير والشر وبين المدنية والهمجية، ولتقضي على كل ما سجلته العصور السالفة من الصور الرائعة للفداء والتضحية في سبيل الحرية وكرامة الإنسان، ولتشوه كل ما أعطته الشرائع السماوية للبشرية من خير وسعادة ولتمحو كل ما ملته المثل الأخلاقية في سجل الأخلاق، ولتضرب بعرض الحائط كل ما أملته العقول النيرة من دليل وبرهان.إن هذه العصابة إذا قدر لها التوفيق في مساعيها الهدامة لكل موازين المنطق والعقل والأخلاق فإنها ستكون الطامة الكبرى والمصيبة العظمى ليست على الإسلام فحسب بل ",
    "_quality_issues": [],
    "format_specific_metadata": {
      "shamela_category": "العقيدة",
      "shamela_publish_date": "26 ذو القعدة 1432",
      "volume_count_raw": "1",
      "author_short": "موسى الموسوي",
      "metadata_volume_count": 1
    }
  },
  "quality_issues": [],
  "processing_time_ms": 5.1,
  "error": null
}