{
  "source_name": "العوامل المؤثرة في نوط الحكم بالمظنة أو بالحكمة.htm",
  "source_path_relative": "العوامل المؤثرة في نوط الحكم بالمظنة أو بالحكمة.htm",
  "status": "success",
  "source_format": "shamela_html",
  "composite_hash": "b057cd62b40b9173f190ac0e8f7de2078488d914472fe0e380dff5415e99f417",
  "file_hashes": {
    "العوامل المؤثرة في نوط الحكم بالمظنة أو بالحكمة.htm": "a347ca4b933d2cf3f5546da418d98ef4771eb17ba06d5c4e3128adb126ac6399"
  },
  "extracted_metadata": {
    "is_multi_volume": false,
    "volume_count": 1,
    "has_muqaddima": false,
    "display_title": "العوامل المؤثرة في نوط الحكم بالمظنة أو بالحكمة",
    "author_short": "أيمن صالح",
    "shamela_category": "أصول الفقه",
    "title_full": "العوامل المؤثرة في نوط الحكم بالمظنة أو بالحكمة - دراسة أصولية",
    "_field_source_title_full": "الكتاب",
    "author_name_raw": "د أيمن صالح",
    "_field_source_author_name_raw": "المؤلف",
    "_extra_card_fields": {
      "بحث منشور في": "مجلة كلية العلوم الإسلامية - بغداد، العدد 70، ذو الحجة 1443 هـ"
    },
    "page_count_raw": "58",
    "_field_source_page_count_raw": "عدد الصفحات",
    "shamela_publish_date": "18 ربيع الآخر 1444",
    "_field_source_shamela_publish_date": "تاريخ النشر بالشاملة",
    "_physical_page_count": 58,
    "body_page_count": 54,
    "page_count": 54,
    "text_sample": "العوامل المؤثِّرة في نوط الحكم بالمظنّة أو بالحكمة: دراسة أصوليّةأيمن صالحأستاذ الفقه وأصولهجامعة قطر\n‌‌الملخّصثَمَّ جدلٌ نظريٌ في كتب الأصول، قديمًا وحديثًا، حولَ القول بجواز أن يُعلَّل الحكم بحكمته، أم يجب أن يُعلَّل بالمظنّة الظاهرة المنضبطة (العلّة). وبالنظر إلى الفروع العملية للفقهاء، فإنّا وجدناهم ينيطون الأحكام بالحكمة نفسها تارةً، وبالمظنة/ العلة تارةً أخرى، فاحتاج الأمر إلى معرفة العوامل التي تؤثّر في اختياراتهم هذه. وبالاستقراء توصّل الباحث إلى تسعة عوامل تؤثِّر في نوط الحكم بالمظنّة أو بالحكمة في الوقائع. الكلمات المفتاحية: التعليل بالحكمة، التعليل بالمظنة، العلة، الحكمة.\n‌‌المقدّمةالحمد لله، والصلاة والسلام على رسول الله، وآله ومن والاه، وبعد:فإنّ علم مقاصد الشريعة بلغ مبلغًا عظيمًا هذه الأزمان، من حيث انتشارُ تناولِه، وكثرةُ المؤلّفات فيه، وهو علمٌ حقيق بالعناية والرعاية، عظيم الفائدة، كبير العائدة، ولاسيّما في تسديد النظر في القضايا الاجتهادية المعاصرة، لكنّه في الوقت نفسه مَزِلّة قدم إذا أُخذ بمعزلٍ عن أصله ومعدنِه، علمِ أصول الفقه، الذي اشتمل على آليّات تحديد المقاصد، وشروطها، وضوابط إعمالها. فالحقيقةُ التاريخية التي لا ينبغي إغفالها هي أنّ علم مقاصد الشريعة فرعٌ عن علم أصول الفقه، عنه انبثق ومنه اشتُق، ولا ينبغي للفرع أن يعود على أصله بالإبطال، وإلا أبطل نفسه.وكثيرٌ من الخائضين في البحث المقاصدي، سيّما من غير المتخصّصين في الأصول، يندفعون بحماسٍ زائد مع المقاصد، أو ما يخالونها المقاصد، من غير تقيُّد بمقرّرات الأصوليين العتيدة في ضوابط تحديدها وإعمالها: إمّا جهلًا بهذه المقرّرات لوعورة مباحثها، ودقّتها، وكثرة الخلاف والخلط فيها في مباحث القياس من كتب الأصول، وإمّا إعراضًا عنها بقصد الالتفاف على الأحكام الشرعيّة التي تفيدها النصوص، وتعطيلِها بذريعة إعمال المقاصد، كما يظهر ذلك جليًّا في كتابات الحداثيين والعَلمانيين أصحاب القراءات الجديدة للنصوص الدينيّة.وفي المقابل هناك طائفةٌ من أهل الشريعة «متحفِّظة» على علم المقاصد برمّته؛ لما تراه من تعسُّف في توظيفه والتذرّع به إلى الافتئات على الشريعة، وتعطيل ظواهرها ونصوصها ومقرّراتها، من قِبَل كثيرين، هم في الغالب دخلاء على العلوم الشرعيّة.\nفبعيدًا عن هذين المسلكين: مسلك المتهاونين، ومسلك المتحفِّظين، يأتي هذا",
    "_quality_issues": [],
    "format_specific_metadata": {
      "shamela_category": "أصول الفقه",
      "shamela_publish_date": "18 ربيع الآخر 1444",
      "page_count_raw": "58",
      "author_short": "أيمن صالح",
      "physical_page_count": 58,
      "extra_card_fields": {
        "بحث منشور في": "مجلة كلية العلوم الإسلامية - بغداد، العدد 70، ذو الحجة 1443 هـ"
      }
    }
  },
  "quality_issues": [],
  "processing_time_ms": 3.4,
  "error": null
}