{
  "source_name": "الشمائل الشريفة - مستل من فيض القدير للمناوي.htm",
  "source_path_relative": "الشمائل الشريفة - مستل من فيض القدير للمناوي.htm",
  "status": "success",
  "source_format": "shamela_html",
  "composite_hash": "2955240fb34e4fdd11965d13b19c142e8b3656260963023726395982fe39a8fa",
  "file_hashes": {
    "الشمائل الشريفة - مستل من فيض القدير للمناوي.htm": "2b832c4f626983e1113ee1eccae954236f22598f2f5797b66d33205b7b324b4f"
  },
  "extracted_metadata": {
    "is_multi_volume": false,
    "volume_count": 1,
    "has_muqaddima": false,
    "display_title": "الشمائل الشريفة - مستل من فيض القدير للمناوي",
    "author_short": "عبد الرؤوف المناوي",
    "shamela_category": "السيرة النبوية",
    "title_full": "الشمائل الشريفة",
    "_field_source_title_full": "الكتاب",
    "_extra_card_fields": {
      "أفرده بالطبع وقدم له": "حسن بن عبيد باحبيشي"
    },
    "publisher": "دار العلم، جدة - السعودية",
    "_field_source_publisher": "الناشر",
    "edition_raw": "الأولى، 1412 هـ - 1991 م",
    "_field_source_edition_raw": "الطبعة",
    "page_count_raw": "376",
    "_field_source_page_count_raw": "عدد الصفحات",
    "editorial_note": "ملحق بآخر المطبوع جدول مقارنة بين تصحيح السيوطي والألباني لأحاديث هذا الباب، وليس ضمن هذه النسخة الإلكترونية",
    "_field_source_editorial_note": "تنبيه",
    "shamela_publish_date": "8 ذو الحجة 1431",
    "_field_source_shamela_publish_date": "تاريخ النشر بالشاملة",
    "_physical_page_count": 376,
    "edition_number": 1,
    "edition_year_hijri": 1412,
    "edition_year_miladi": 1991,
    "body_page_count": 363,
    "page_count": 363,
    "text_sample": "‌‌(تَعْرِيف بِالْإِمَامِ الْمَنَاوِيّ «952 - 1031 هـ = 1545 - 1622 م» ) مُحَمَّد عبد الرؤوف بن تَاج العارفين ابْن عَليّ بن زيد العابدين الحدادي ثمَّ الْمَنَاوِيّ القاهري، زين الدّين: من كبار الْعلمَاء بِالدّينِ والفنون. انزوى للبحث والتصنيف، وَكَانَ قَلِيل الطَّعَام كثير السهر، فَمَرض وضعفت أَطْرَافه، فَجعل وَلَده تَاج الدّين مُحَمَّد يستملي مِنْهُ تآليفه. لَهُ نَحْو ثَمَانِينَ مصنفا، مِنْهَا الْكَبِير وَالصَّغِير والتام والناقص، عَاشَ فِي الْقَاهِرَة، وَتُوفِّي بهَا، من كتبه «كنوز الْحَقَائِق - ط» فِي الحَدِيث، و «التَّيْسِير - ط» فِي شرح الْجَامِع الصَّغِير مجلدان، اخْتَصَرَهُ من شَرحه الْكَبِير «فيض - الْقَدِير - ط» وَشرح «الشَّمَائِل لِلتِّرْمِذِي - ط» و «الْكَوَاكِب الدرية فِي تراجم السَّادة الصُّوفِيَّة - ط» فِي جزءين و «شرح قصيدة النَّفس، العينية لِابْنِ سينا - ط» و «الْجَوَاهِر المضيئة فِي الْآدَاب السُّلْطَانِيَّة - خَ» و «سيرة عمر بن عبد الْعَزِيز - خَ» و «تيسير الْوُقُوف على غوامض أَحْكَام الْوُقُوف - خَ» و «غَايَة الْإِرْشَاد إِلَى معرفَة أَحْكَام الْحَيَوَان والنبات والجماد - خَ» و «اليواقيت والدرر - خَ» فِي الحَدِيث، و «الفتوحات السبحانية - خَ» فِي شرح ألفية الْعِرَاقِيّ، فِي السِّيرَة النَّبَوِيَّة، و «الصفوة - خَ» فِي مَنَاقِب آل الْبَيْت، و «الطَّبَقَات الصُّغْرَى - خَ» وَيُسمى إرغام أَوْلِيَاء الشَّيْطَان، و «شرح الْقَامُوس الْمُحِيط - خَ» الأول مِنْهُ، و «آدَاب الْأكل وَالشرب - خَ» و «الدّرّ المنضود فِي ذمّ الْبُخْل ومدح الْجُود - خَ» و «التَّوْقِيف على مهمات التعاريف - خَ» ذيل لتعريفات الْجِرْجَانِيّ، و «بغية الْمُحْتَاج فِي معرفَة أصُول الطِّبّ والعلاج» و «تَارِيخ الْخُلَفَاء» و «عماد البلاغة» فِي الْأَمْثَال، وَكتاب فِي «التشريح وَالروح وَمَا بِهِ صَلَاح الْإِنْسَان وفساده» و «إحكام الأساس» اختصر بِهِ أساس البلاغة ورتبه كالقاموس.\n‌‌(مُقَدّمَة المُصَنّف) الْحَمد لله الَّذِي بعث على رَأس كل مائَة سنة من يجدد لهَذِهِ الْأمة أَمر دينهَا وَأقَام فِي كل عصر من يحوط هَذِه الْملَّة بتشييد أَرْكَانهَا وتأييد سننها وتبيينها، وَأشْهد أَن لَا إِلَه إِلَّا الله وَحده لَا شريك لَهُ: شَهَادَة يزيح ظلام الشكوك صبح يقينها، وَأشْهد أَن سيدنَا مُحَمَّدًا عَبده وَ",
    "_quality_issues": [],
    "format_specific_metadata": {
      "shamela_category": "السيرة النبوية",
      "shamela_publish_date": "8 ذو الحجة 1431",
      "editorial_note": "ملحق بآخر المطبوع جدول مقارنة بين تصحيح السيوطي والألباني لأحاديث هذا الباب، وليس ضمن هذه النسخة الإلكترونية",
      "edition_raw": "الأولى، 1412 هـ - 1991 م",
      "page_count_raw": "376",
      "author_short": "عبد الرؤوف المناوي",
      "physical_page_count": 376,
      "extra_card_fields": {
        "أفرده بالطبع وقدم له": "حسن بن عبيد باحبيشي"
      }
    }
  },
  "quality_issues": [],
  "processing_time_ms": 15.5,
  "error": null
}