{
  "source_name": "الوجيز في شرح قراءات القرأة الثمانية أئمة الأمصار الخمسة.htm",
  "source_path_relative": "الوجيز في شرح قراءات القرأة الثمانية أئمة الأمصار الخمسة.htm",
  "status": "success",
  "source_format": "shamela_html",
  "composite_hash": "fa0062c44e6a7e25d394aa17bc6d20762dc297d6617bfbcb6c7d738572d8bcc8",
  "file_hashes": {
    "الوجيز في شرح قراءات القرأة الثمانية أئمة الأمصار الخمسة.htm": "a68bdab9288023ffd144ed056960afc9d177f996c7d09e59d05806c118f69a12"
  },
  "extracted_metadata": {
    "is_multi_volume": false,
    "volume_count": 1,
    "has_muqaddima": false,
    "display_title": "الوجيز في شرح قراءات القرأة الثمانية أئمة الأمصار الخمسة",
    "author_short": "الأهوازي",
    "shamela_category": "التجويد والقراءات",
    "title_full": "الوجيز في شرح قراءات القرأة الثمانية أئمة الأمصار الخمسة",
    "_field_source_title_full": "الكتاب",
    "author_name_raw": "أبو علي الحسن بن علي بن إبراهيم بن يزداد الأَهْوَازي (ت 446هـ)",
    "_field_source_author_name_raw": "المؤلف",
    "muhaqiq_name_raw": "دريد حسن أحمد",
    "_field_source_muhaqiq_name_raw": "المحقق",
    "publisher": "دار الغرب الإسلامى - بيروت",
    "_field_source_publisher": "الناشر",
    "edition_raw": "الأولى، 2002 م",
    "_field_source_edition_raw": "الطبعة",
    "page_count_raw": "448",
    "_field_source_page_count_raw": "عدد الصفحات",
    "shamela_publish_date": "2 محرم 1433",
    "_field_source_shamela_publish_date": "تاريخ النشر بالشاملة",
    "author_death_hijri": 446,
    "author_name_clean": "أبو علي الحسن بن علي بن إبراهيم بن يزداد الأَهْوَازي",
    "_physical_page_count": 448,
    "edition_number": 1,
    "edition_year_miladi": 2002,
    "body_page_count": 441,
    "page_count": 441,
    "text_sample": "‌‌[مقدمات التحقيق]‌‌تقديم [للدكتور بشار عواد معروف]لأستاذنا العلامة الدكتور بشار عواد معروف بسم الله الرّحمن الرّحيم الْحَمْدُ لِلَّهِ الَّذِي أَنْزَلَ عَلى عَبْدِهِ الْكِتابَ وَلَمْ يَجْعَلْ لَهُ عِوَجاً (1) قَيِّماً لِيُنْذِرَ بَأْساً شَدِيداً مِنْ لَدُنْهُ وَيُبَشِّرَ الْمُؤْمِنِينَ الَّذِينَ يَعْمَلُونَ الصَّالِحاتِ أَنَّ لَهُمْ أَجْراً حَسَناً (2) [الكهف].نحمده ونستعينه ونستغفره، ونعوذ بالله من شرور أنفسنا ومن سيئات أعمالنا، من يهده الله فلا مضل له، ومن يضلل فلا هادي له، وأشهد أن لا إله إلا الله وحده لا شريك له- كلمة قامت بها الأرض والسموات وخلقت لأجلها جميع المخلوقات- وأشهد أن سيدنا وإمامنا وقدوتنا محمدا عبده ورسوله، وأمينه على وحيه، وخيرته من خلقه، وسفيره بينه وبين عباده، بعثه الله بالهدى ودين الحق ليظهره على الدين كلّه ولو كره المشركون.أما بعد، فإن القرآن الكريم هو كتاب الله الذي لا يأتيه الباطل من بين يديه ولا من خلفه تنزيل من حكيم حميد، وهو «نوره المبين الذي أشرقت له الظّلمات، ورحمته المهداة التي بها صلاح جميع المخلوقات، والسبب الواصل بينه وبين عباده إذا انقطعت الأسباب، وبابه الأعظم الذي منه الدخول فلا يغلق إذا غلّقت الأبواب، وهو الصراط المستقيم الذي لا تميل به الآراء، والذّكر الحكيم الذي لا تزيغ به الأهواء، والنّزل الكريم الذي لا يشبع منه العلماء؛ لا تفنى عجائبه، ولا تقلع سحائبه، ولا تنقضي آياته، ولا تختلف دلالاته، كلما ازدادت البصائر فيه تأملا وتفكيرا زادها هداية وتبصيرا، فهو نور البصائر من عماها، وشفاء الصّدور من أدوائها وجواها، وحياة القلوب، ولذة النفوس، وحادي الأرواح إلى بلاد الأفراح والمنادي بالمساء والصباح: يا أهل الفلاح حيّ على الفلاح «1»».وقد أمرنا الله جل شأنه ورسوله بتلاوته وتعاهده وتدبّره والعمل به، فقال جل ثناؤه: كِتابٌ أَنْزَلْناهُ إِلَيْكَ مُبارَكٌ لِيَدَّبَّرُوا آياتِهِ وَلِيَتَذَكَّرَ أُولُوا الْأَلْبابِ [ص]، وقال رسوله صلى الله عليه وسلم «خيركم من تعلّم القرآن وعلّمه» «2»، وثبت عنه صلى الله عليه وسلم أنه قال: «المؤمن الذي يقرأ القرآن\nويعمل به، كالأترجة طعمها طيب وريحها طيب» «1».ولحكمة بالغة أنزل الله جل ثناؤه كتابه باللسان العربي المبين، وجعله المعجزة الكبرى لرسوله الكريم صلى الله عليه وسلم، فكان أهل العربية من أحق الخلق بفهمه وتدبر معاني",
    "_quality_issues": [],
    "format_specific_metadata": {
      "shamela_category": "التجويد والقراءات",
      "shamela_publish_date": "2 محرم 1433",
      "edition_raw": "الأولى، 2002 م",
      "page_count_raw": "448",
      "author_short": "الأهوازي",
      "physical_page_count": 448
    }
  },
  "quality_issues": [],
  "processing_time_ms": 17.0,
  "error": null
}