{
  "source_name": "الثاني من أجزاء أبي علي بن شاذان.htm",
  "source_path_relative": "الثاني من أجزاء أبي علي بن شاذان.htm",
  "status": "success",
  "source_format": "shamela_html",
  "composite_hash": "a1b275fd524c174816ed22c9749f7c81b71044088fc6cecce6038d6c8b80a454",
  "file_hashes": {
    "الثاني من أجزاء أبي علي بن شاذان.htm": "5376492f43e3e252e00513f2594216384a3fdb4655dfc910ac4deb7b7273a32d"
  },
  "extracted_metadata": {
    "is_multi_volume": false,
    "volume_count": 1,
    "has_muqaddima": false,
    "display_title": "الثاني من أجزاء أبي علي بن شاذان",
    "author_short": "الحسن بن خلف بن شاذان",
    "shamela_category": "كتب السنة",
    "title_full": "الثاني من أجزاء أبي علي بن شاذان",
    "_field_source_title_full": "الكتاب",
    "author_name_raw": "الحسن بن خلف بن شاذان بن زياد الواسطى، أبو على البزاز (ت 246هـ)",
    "_field_source_author_name_raw": "المؤلف",
    "publisher": "مخطوط نُشر في برنامج جوامع الكلم المجاني التابع لموقع الشبكة الإسلامية",
    "_field_source_publisher": "الناشر",
    "edition_raw": "الأولى، 2004",
    "_field_source_edition_raw": "الطبعة",
    "page_count_raw": "123",
    "_field_source_page_count_raw": "عدد الصفحات",
    "shamela_publish_date": "8 ذو الحجة 1431",
    "_field_source_shamela_publish_date": "تاريخ النشر بالشاملة",
    "author_death_hijri": 246,
    "author_name_clean": "الحسن بن خلف بن شاذان بن زياد الواسطى، أبو على البزاز",
    "_physical_page_count": 123,
    "edition_number": 1,
    "edition_year_miladi": 2004,
    "body_page_count": 123,
    "page_count": 123,
    "text_sample": "جُزْءٌ مِنْ رِوَايَةِ الشَّيْخِ أَبِي عَلِيٍّ الْحَسَنِ بْنِ أَحْمَدَ بْنِ إِبْرَاهِيمَ بْنِ الْحَسَنِ بْنِ خَلَفِ بْنِ شَاذَانَ، عَنْهُ. . . . . . . أَنَّ أَبَا بَكْرٍ قَالَ: يَا رَسُولَ اللَّهِ قَدْ شِبْتَ.قَالَ: «شَيَّبَتْنِي هُودٌ وَأَخَوَاتُهَا، وَعَمَّ يَتَسَاءَلُونَ، وَالْوَاقِعَةُ ، وَالْمُرْسَلاتُ، وَإِذَا الشَّمْسُ كُوِّرَتْ»\n1 - أَخْبَرَنَا مُحَمَّدٌ، قَالَ: ثنا مُحَمَّدُ بْنُ الْفَرَجِ، قَالَ: ثنا عُبَيْدُ اللَّهِ بْنُ مُوسَى، أَخْبَرَنَا شَيْبَانُ، عَنْ يَحْيَى بْنِ أَبِي كَثِيرٍ، عَنْ أَبِي سَلَمَةَ، عَنْ عُمَرَ بْنِ عَبْدِ الْعَزِيزِ، عَنْ عُرْوَةَ، عَنْ عَائِشَةَ رضي الله عنها، أَنَّ النَّبِيَّ صَلَّى اللَّهُ عَلَيْهِ «كَانَ‌‌ يُقَبِّلُ وَهُوَ صَائِمٌ»\n2 - أَخْبَرَنَا مُحَمَّدٌ، قَالَ: ثنا مُحَمَّدُ بْنُ الْفَرَجِ، قَالَ: ثنا عَبْدُ الْعَزِيزِ بْنُ أَبَانٍ، قَالَ: ثنا سُفْيَانُ الثَّوْرِيُّ، عَنْ عَاصِمِ بْنِ أَبِي النَّجُودِ، عَنْ زِرِّ بْنِ حُبَيْشٍ، عَنْ عَبْدِ اللَّهِ ، \"‌‌ أَنَّ الَّذِينَ هَبَطُوا عَلَى رَسُولِ اللَّهِ صَلَّى اللَّهُ عَلَيْهِ بِبَطْنِ نَخْلَةٍ مِنْهُمْ زَوْبَعَةُ مِنْ جِنِّ نَصِيبِينَ وَهُوَ يَقْرَأُ، فَقَالَ: صَهْ صَهْ ، فَسَمِعُوا وَأَنْصَتُوا \"\n3 - أَخْبَرَنَا مُحَمَّدٌ، قَالَ: نا مُحَمَّدٌ، قَالَ: نا عُبَيْدُ اللَّهِ بْنُ مُوسَى، قَالَ: أَخْبَرَنَا حَنْظَلَةُ، عَنْ سَالِمٍ، عَنِ ابْنِ عُمَرَ، قَالَ: قَالَ رَسُولُ اللَّهِ صَلَّى اللَّهُ عَلَيْهِ: \"‌‌ لأَنْ يَمْتَلِئَ جَوْفُ أَحَدِكُمْ قَيْحًا خَيْرٌ لَهُ مِنْ أَنْ يَمْتَلِئَ شِعْرًا\n4 - أَخْبَرَنَا مُحَمَّدٌ، قَالَ: ثنا مُحَمَّدُ بْنُ يُوسُفَ بْنِ الطَّبَّاعِ، قَالَ: سَمِعْتُ زَيْدَ بْنَ هَارُونَ، قَالَ: أَخْبَرَنَا سُفْيَانُ بْنُ حُسَيْنٍ، عَنِ الزُّهْرِيِّ، عَنْ أَنَسٍ، أَنَّ النَّبِيَّ صَلَّى اللَّهُ عَلَيْهِ ، قَالَ‌‌ يَوْمَ حُنَيْنٍ: «اللَّهُمَّ إِنْ تَشَأْ لا تُعْبَدُ بَعْدَ الْيَوْمِ» .كَذَا قَالَ: عَنِ الزُّهْرِيِّ، عَنْ أَنَسٍ\n5 - أَخْبَرَنَا مُحَمَّدٌ، قَالَ: ثنا أحْمَدُ بْنُ سَعِيدٍ الْحَمَّالُ، عَنْ قَبِيصَةَ، ثنا سُفْيَانُ، عَنْ عَبْدِ اللَّهِ بْنِ دِينَارٍ، قَالَ: سَمِعْتُ ابْنَ عُمَرَ، يَقُولُ: قَالَ رَسُولُ اللَّهِ: ‌‌«مَنْ أُرِيدَ مَالُهُ بِغَيْرِ حَقٍّ فَقَا",
    "_quality_issues": [],
    "format_specific_metadata": {
      "shamela_category": "كتب السنة",
      "shamela_publish_date": "8 ذو الحجة 1431",
      "edition_raw": "الأولى، 2004",
      "page_count_raw": "123",
      "author_short": "الحسن بن خلف بن شاذان",
      "physical_page_count": 123
    }
  },
  "quality_issues": [],
  "processing_time_ms": 2.1,
  "error": null
}