{
  "source_name": "تعليقات الدارقطني على المجروحين لابن حبان.htm",
  "source_path_relative": "تعليقات الدارقطني على المجروحين لابن حبان.htm",
  "status": "success",
  "source_format": "shamela_html",
  "composite_hash": "92d7646bde9e4e79cb3d316fa07c31cf2eb882da9fb7b17f2f23b987fe04093b",
  "file_hashes": {
    "تعليقات الدارقطني على المجروحين لابن حبان.htm": "a9b6f115aea15749c15a45ee688b163a2715e30232bd5d5707b80ebf62316f6a"
  },
  "extracted_metadata": {
    "is_multi_volume": false,
    "volume_count": 1,
    "has_muqaddima": false,
    "display_title": "تعليقات الدارقطني على المجروحين لابن حبان",
    "author_short": "الدارقطني",
    "shamela_category": "التراجم والطبقات",
    "title_full": "تعليقات الدارقطني على المجروحين لابن حبان",
    "_field_source_title_full": "الكتاب",
    "author_name_raw": "أبو الحسن علي بن عمر بن أحمد بن مهدي بن مسعود بن النعمان بن دينار البغدادي الدارقطني (ت 385هـ)",
    "_field_source_author_name_raw": "المؤلف",
    "muhaqiq_name_raw": "خليل بن محمد العربي",
    "_field_source_muhaqiq_name_raw": "تحقيق",
    "publisher": "الفاروق الحديثة للطباعة والنشر، دار الكتاب الإسلامي - القاهرة",
    "_field_source_publisher": "الناشر",
    "edition_raw": "الأولى، 1414 هـ - 1994 م",
    "_field_source_edition_raw": "الطبعة",
    "page_count_raw": "296",
    "_field_source_page_count_raw": "عدد الصفحات",
    "shamela_publish_date": "8 ذو الحجة 1431",
    "_field_source_shamela_publish_date": "تاريخ النشر بالشاملة",
    "author_death_hijri": 385,
    "author_name_clean": "أبو الحسن علي بن عمر بن أحمد بن مهدي بن مسعود بن النعمان بن دينار البغدادي الدارقطني",
    "_physical_page_count": 296,
    "edition_number": 1,
    "edition_year_hijri": 1414,
    "edition_year_miladi": 1994,
    "body_page_count": 256,
    "page_count": 256,
    "text_sample": "حَدَّثَنَا مُحَمَّدُ بْنُ مَحْمُودِ بْنِ عَدِيٍّ النَّسَائِيُّ، قَالَ: ثَنَا حُمَيْدُ بْنُ زَنْجُوَيْهِ، قَالَ: ثَنَا يَعْلَى بْنُ عُبَيْدٍ، قَالَ: ثَنَا مُحَمَّدُ بْنُ إِسْحَاقَ، عَنِ الزُّهْرِيِّ، عَنْ مُحَمَدِ بْنِ جُبَيْرِ بْنِ مُطْعَمٍ، عَنْ أَبِيهِ، قَالَ: «قَامَ رَسُولُ اللَّهِ صلى الله عليه وسلم بِالْخَيْفِ مِنْ مِنًى» . . . . . . . . . . . . . . . الْحَدِيثَ.قَالَ أَبُو الْحَسَنِ: لَمْ يَسْمَعْ هَذَا الْحَدِيثَ مُحَمَّدُ بْنُ إِسْحَاقَ مِنَ الزُّهْرِيِّ، إِنَّمَا سَمِعَهُ مِنْ عَبْدِ السَّلامِ بْنِ أَبِي الْجَنُوبِ، عَنِ الزُّهْرِيِّ.كَذَلِكَ قَالَ ابْنُ نُمَيْرٍ، عَنْ مُحَمَدِ بْنِ إِسْحَاقَ، وَقَدْ رُوِيَ هَذَا الْحَدِيثُ عَنْ مَالِكِ بْنِ أَنَسٍ، عَنِ الزُّهْرِيِّ، كَذَلِكَ تَفَرَّدَ بِهِ عَبْدُ اللَّهِ بْنُ مُحَمَدِ بْنِ رَبِيعَةَ الْقُدَامِيُّ، عَنْ مَالِكٍقَالَ ابْنُ حِبَّانَ: حَدَّثَنَا أَحْمَدُ بْنُ يَحْيَى بْنِ زُهَيْرٍ بِتُسْتَرَ، قَالَ: ثَنَا مُحَمَّدُ بْنُ الْحُسَيْنِ بْنِ إِشْكَابَ، قَالَ: ثَنَا عَلِيُّ بْنُ حَفْصٍ الْمَدَائِنِيُّ، قَالَ: ثَنَا\nشُعْبَةُ، عَنْ خُبَيْبِ بْنِ عَبْدِ الرَّحْمَنِ، عَنْ حَفْصِ بْنِ عَاصِمٍ، عَنْ أَبِي هُرَيْرَةَ، قَالَ: قَالَ رَسُولُ اللَّهِ صلى الله عليه وسلم: «كَفَى بِالْمَرْءِ إِثْمًا أَنْ يُحَدِّثَ بِكُلِّ مَا سَمِعَ» .قَالَ أَبُو الْحَسَنِ: هَذَا حَدِيثٌ رَوَاهُ غُنْدَرٌ، وَابْنُ أَبِي عَدِيٍّ، وَغَيْرُهُمَا، عَنْ شُعْبَةَ، مُرْسَلا، لَمْ يَذْكُرُوا فِيهِ أَبَا هُرَيْرَةَ ، وَذَكَرَهُ عَلِيُّ بْنُ حَفْصٍ الْمَدَائِنِيُّ، وَغَيْرُهُ أَثْبَتُ مِنْهُقَالَ ابْنُ حِبَّانَ حَدَّثَنَا عَبْدُ اللَّهِ بْنُ قَحْطَبَةَ بِفَمِ الصُّلْحِ، ثَنَا أَحْمَدُ بْنُ زَكَرِيَّا\nالْوَاسِطِيُّ، قَالَ: سَمِعْتُ أَبَا الْحَارِثِ الْوَرَّاقَ، يَقُولُ: جَلَسْنَا عَلَى بَابِ شُعْبَةَ نَتَذَاكَرُ السَّنَدَ.قَالَ أَبُو الْحَسَنِ: أَبُو الْحَارِثِ الْوَرَّاقُ اسْمُهُ نَصْرُ بْنُ حَمَّادٍ.قَالَ ابْنُ حِبَّانَ حَدَّثَنَا عَبْدُ الْكَبِيرِ بْنُ عُمَرَ الْخَطَّابِيُّ بِالْبَصْرَةِ، ثَنَا أَحْمَدُ بْنُ سِنَانٍ، قَالَ: سَمِعْتُ عَبْدَ الرَّحْمَنِ بْنَ مَهْدِيٍّ، يَقُولُ: لَمَّا حَدَّثَنَا سُفْيَانُ، عَنْ حَمَّادٍ، عَنْ عَمْرِو بْنِ عَطِيَّةَ التَّيْ",
    "_quality_issues": [],
    "format_specific_metadata": {
      "shamela_category": "التراجم والطبقات",
      "shamela_publish_date": "8 ذو الحجة 1431",
      "edition_raw": "الأولى، 1414 هـ - 1994 م",
      "page_count_raw": "296",
      "author_short": "الدارقطني",
      "physical_page_count": 296
    }
  },
  "quality_issues": [],
  "processing_time_ms": 7.8,
  "error": null
}