{
  "source_name": "عبق الرياحين في سيرة ذي الجناحين.htm",
  "source_path_relative": "عبق الرياحين في سيرة ذي الجناحين.htm",
  "status": "success",
  "source_format": "shamela_html",
  "composite_hash": "014ead3c1d8f004ed2919aa67de48490d37a03c6c991df16a73c81898aea00c1",
  "file_hashes": {
    "عبق الرياحين في سيرة ذي الجناحين.htm": "0e8c9a9a4e33892ca18e0a41a3deda8343366004bfaeb266a33098805f07bd80"
  },
  "extracted_metadata": {
    "is_multi_volume": false,
    "volume_count": 1,
    "has_muqaddima": false,
    "display_title": "عبق الرياحين في سيرة ذي الجناحين",
    "author_short": "نايف منير فارس",
    "shamela_category": "التراجم والطبقات",
    "title_full": "عبق الرياحين في سيرة ذي الجناحين جعفر بن أبي طالب وآله رضي الله عنهم",
    "_field_source_title_full": "الكتاب",
    "author_name_raw": "د. نايف منير فارس",
    "_field_source_author_name_raw": "المؤلف",
    "muhaqiq_name_raw": "مركز البحوث والدراسات بالمبرة",
    "_field_source_muhaqiq_name_raw": "مراجعة وتنقيح",
    "publisher": "مبرة الآل والأصحاب، الكويت",
    "_field_source_publisher": "الناشر",
    "edition_raw": "الأولى، 1432 هـ - 2011 م",
    "_field_source_edition_raw": "الطبعة",
    "page_count_raw": "256",
    "_field_source_page_count_raw": "عدد الصفحات",
    "preparer": "«مبرة الآل والأصحاب»، جزاهم الله خيرا",
    "_field_source_preparer": "قدمه للشاملة",
    "shamela_publish_date": "8 ربيع الأول 1443",
    "_field_source_shamela_publish_date": "تاريخ النشر بالشاملة",
    "_physical_page_count": 256,
    "edition_number": 1,
    "edition_year_hijri": 1432,
    "edition_year_miladi": 2011,
    "body_page_count": 251,
    "page_count": 251,
    "text_sample": "مبرة الآل والأصحابسلسلة سير الآل والصحاب (15)  عبق الرياحين في سيرة ذي الجناحينجعفر بن أبي طالب وآله رضي الله عنهم د. نايف منير فارسمراجعة وتنقيح مركز البحوث والدراسات بالمبرة\nالإمام جعفر بن أبي طالب وآله رضي الله عنهم نايف منير فارس مراجعة وتنقيحمركز البحوث والدراسات بالمبرة\nفهرسة مكتبة الكويت الوطنية أثناء النشر حقوق الطبع محفوظة لمبرة الآل والأصحابإلا لمن أراد التوزيع الخيري بشرط عدم التصرف في المادة الطبعة الأولى1432 هـ / 2011 م هاتف: 22560203 - 22552340 فاكس: 22560346ص. ب: 12421 الشامية الرمز البريدي 71655 الكويتE-mail: almabarrh@gmail.comwww.almabarrah.net\n‌‌المقدمةإن الحمد لله نحمده ونستعينه، ونستهديه ونستغفره، ونعوذ بالله من شرور أنفسنا، وسيئات أعمالنا، من يهده الله فلا مضل له، ومن يضلل فلا هادي له، وأشهد أن لا إله إلا الله، وحده لا شريك له، وأشهد أن محمداً عبدُهُ ورسولُهُ. أما بعد: فلقد منَّ الله علينا بأن جعلنا مسلمين مؤمنين متبعين لأوامره منتهجين نهج رسوله صلى الله عليه وآله وسلم، وصحابته الكرام رضي الله عنهم أجمعين، فهم من نقل لنا الدين وتعاليمه، وعن طريقهم وصل إلينا القرآن الذي حفظه الله تعالى من التحريف والتبديل، ووصلت إلينا أحاديث رسولنا صلى الله عليه وآله وسلم المبيِّنة والمفصِّلة لما في القرآن من إجمال. وهي أيضاً محفوظة بحفظ الدين، فقيَّض الله لها علماء يمحِّصون الصحيح منها من الضعيف والموضوع. ولهذا كان الطعن في حياة أصحاب النبي صلى الله عليه وآله وسلم طعناً في الدين واستهدافاً للإسلام. إذ كيف لمسلم يؤمن بالله ورسوله أن يطعن في أناس ائتمنهم الله ورسوله صلى الله عليه وآله وسلم على نقل الإسلام. قال تعالى: {وَالسَّابِقُونَ الْأَوَّلُونَ مِنَ الْمُهَاجِرِينَ وَالْأَنْصَارِ وَالَّذِينَ اتَّبَعُوهُمْ بِإِحْسَانٍ رَضِيَ اللَّهُ عَنْهُمْ وَرَضُوا عَنْهُ وَأَعَدَّ لَهُمْ جَنَّاتٍ تَجْرِي تَحْتَهَا الْأَنْهَارُ خَالِدِينَ\nفِيهَا أَبَدًا ذَلِكَ الْفَوْزُ الْعَظِيمُ}(1). ومما نقله الصحابة رضي الله عنهم، أيضاً - إلى جانب كتاب ربهم وسنة نبيهم وسيرته العطرة صلى الله عليه وآله وسلم سير إخوانهم أصحاب رسول الله صلى الله عليه وآله وسلم من أهل البيت الطاهرين، ومن غيرهم رضوان الله عليهم أجمعين، ومن تلك السير العظيمة، سيرة الشيهد ابن عم رسو الله صلى الله عليه وآله وسلم ذ",
    "_quality_issues": [],
    "format_specific_metadata": {
      "shamela_category": "التراجم والطبقات",
      "shamela_publish_date": "8 ربيع الأول 1443",
      "edition_raw": "الأولى، 1432 هـ - 2011 م",
      "page_count_raw": "256",
      "author_short": "نايف منير فارس",
      "preparer": "«مبرة الآل والأصحاب»، جزاهم الله خيرا",
      "physical_page_count": 256
    }
  },
  "quality_issues": [],
  "processing_time_ms": 12.4,
  "error": null
}