{
  "source_name": "كرامات الأولياء للالكائي - من شرح أصول اعتقاد أهل السنة والجماعة للالكائي.htm",
  "source_path_relative": "كرامات الأولياء للالكائي - من شرح أصول اعتقاد أهل السنة والجماعة للالكائي.htm",
  "status": "success",
  "source_format": "shamela_html",
  "composite_hash": "f8cb6c859808dfdbe995cca13dbed0b56e350e562f7a5b28726b2fab7fc09cb7",
  "file_hashes": {
    "كرامات الأولياء للالكائي - من شرح أصول اعتقاد أهل السنة والجماعة للالكائي.htm": "a7cd068f2802fc13a1df72c09f3c7db855b2c3ba11cce8a60eb542cdf528d679"
  },
  "extracted_metadata": {
    "is_multi_volume": false,
    "volume_count": 1,
    "has_muqaddima": false,
    "display_title": "كرامات الأولياء للالكائي - من شرح أصول اعتقاد أهل السنة والجماعة للالكائي",
    "author_short": "اللالكائي",
    "shamela_category": "كتب السنة",
    "title_full": "كرامات الأولياء للالكائي - من كتاب شرح أصول اعتقاد أهل السنة والجماعة للالكائي",
    "_field_source_title_full": "الكتاب",
    "author_name_raw": "أبو القاسم هبة الله بن الحسن بن منصور الطبري الرازي اللالكائي (ت 418 هـ)",
    "_field_source_author_name_raw": "المؤلف",
    "muhaqiq_name_raw": "أحمد بن سعد بن حمدان الغامدي [ت 1434 هـ]",
    "_field_source_muhaqiq_name_raw": "تحقيق",
    "publisher": "دار طيبة - السعودية",
    "_field_source_publisher": "الناشر",
    "edition_raw": "الثامنة، 1423 هـ / 2003 م",
    "_field_source_edition_raw": "الطبعة",
    "volume_count_raw": "1 (هو الجزء 9 من كتاب شرح أصول اعتقاد أهل السنة والجماعة)",
    "_field_source_volume_count_raw": "عدد الأجزاء",
    "shamela_publish_date": "8 ذو الحجة 1431",
    "_field_source_shamela_publish_date": "تاريخ النشر بالشاملة",
    "author_death_hijri": 418,
    "author_name_clean": "أبو القاسم هبة الله بن الحسن بن منصور الطبري الرازي اللالكائي",
    "muhaqiq_death_hijri": 1434,
    "muhaqiq_name_clean": "أحمد بن سعد بن حمدان الغامدي",
    "edition_number": 8,
    "edition_year_hijri": 1423,
    "edition_year_miladi": 2003,
    "_metadata_volume_count": 1,
    "body_page_count": 319,
    "page_count": 319,
    "text_sample": "‌‌سِيَاقُ مَا دَلَّ مِنْ كِتَابِ اللَّهِ عز وجل وَمَا رُوِيَ عَنِ النَّبِيِّ صلى الله عليه وسلم وَالصَّحَابَةِ رضي الله عنهم وَالتَّابِعِينَ مِنْ بَعْدِهِمْ والْخَالِفِينَ لَهُمْ رَحْمَةُ اللَّهِ عَلَيْهِمْ فِي كَرَامَةِ أَوْلِيَاءِ اللَّهِ تَعَالَى وَإِظْهَارِ الْآيَاتِ فِيهِمْ لِيَزْدَادَ الْمُؤْمِنُونَ إِيمَانًا وَالْمُرْتَابُونَ بِهَا خَسَارًافَأَمَّا الْكِتَابُ فَقَوْلُهُ تَعَالَى فِي قِصَّةِ مَرْيَمَ عليها السلام: {كُلَّمَا دَخَلَ عَلَيْهَا زَكَرِيَّا الْمِحْرَابَ وَجَدَ عِنْدَهَا رِزْقًا قَالَ يَا مَرْيَمُ أَنَّى لَكِ هَذَا قَالَتْ هُوَ مِنْ عِنْدِ اللَّهِ إِنَّ اللَّهَ يَرْزُقُ مَنْ يَشَاءُ بِغَيْرِ حِسَابٍ} [آل عمران: 37] فَرُوِيَ عَنِ ابْنِ عَبَّاسٍ، فِي تَفْسِيرِ هَذِهِ الْآيَةِ قَالَ: وَجَدَ عِنْدَهَا الْفَاكِهَةَ الْغَضَّةَ حِينَ لَا تُوجَدُ الْفَاكِهَةُ عِنْدَ أَحَدٍ فَكَانَ زَكَرِيَّا يَقُولُ: يَا مَرْيَمُ أَنَّى لَكِ هَذَا؟ قَالَتْ: هُوَ مِنْ عِنْدِ اللَّهِ، إِنَّ اللَّهَ يَرْزُقُ مَنْ يَشَاءُ بِغَيْرِ حِسَابٍ وَرُوِيَ عَنْهُ قَالَ: عِنَبًا فِي مِكْتَلٍ فِي غَيْرِ حِينِهِ، 1 - وَعَنْ سَعِيدِ بْنِ جُبَيْرٍ، وَمُجَاهِدٍ، وَعِكْرِمَةَ، وَجَابِرِ بْنِ زَيْدٍ، وَإِبْرَاهِيمَ النَّخَعِيِّ، وَقَتَادَةَ، وَالرَّبِيعِ بْنِ أَنَسِ، وَعَطِيَّةَ، وَالسُّدِّيِّ، وَسُفْيَانَ الثَّوْرِيِّ ⦗ص: 73⦘ فَاكِهَةَ الشِّتَاءِ فِي الصَّيْفِ، وَفَاكِهَةَ الصَّيْفِ فِي الشِّتَاءِ، وَقَالَ تبارك وتعالى فِي قِصَّةِ سَارَةَ زَوْجَةِ إِبْرَاهِيمَ الْخَلِيلِ صلى الله عليه وسلم: {وَامْرَأَتُهُ قَائِمَةٌ فَضَحِكَتْ فَبَشَّرْنَاهَا بِإِسْحَاقَ وَمِنْ وَرَاءِ إِسْحَاقَ يَعْقُوبَ، قَالَتْ يَا وَيْلَتَى أَأَلِدُ وَأَنَا عَجُوزٌ وَهَذَا بَعْلِي شَيْخًا إِنَّ هَذَا لَشَيْءٌ عَجِيبٌ، قَالُوا أَتَعْجَبِينَ مِنْ أَمْرِ اللَّهِ رَحْمَةُ اللَّهِ وَبَرَكَاتُهُ عَلَيْكُمْ أَهْلَ الْبَيْتِ إِنَّهُ حَمِيدٌ مَجِيدٌ} 2 - فَرُوِيَ عَنْ ضَمْرَةَ بْنِ حَبِيبٍ فِي تَفْسِيرِهِ أَنَّ سَارَةَ لَمَّا بَشَّرَهَا الرُّسُلُ بِإِسْحَاقَ قَالَ: فَبَيْنَمَا هِيَ تَمْشِي وَتُحَدِّثُهُمْ حِينَ آنَسَتْ بِالْحَيْضَةِ فَحَاضَتْ قَبْلَ أَنْ تَحْمِلَ بِإِسْحَاقَ وَكَانَ قَوْلُهَا لِلرُّسُلِ حِينَ بَشَّرُوهَا بِإِسْحَاقَ:",
    "_quality_issues": [],
    "format_specific_metadata": {
      "shamela_category": "كتب السنة",
      "shamela_publish_date": "8 ذو الحجة 1431",
      "volume_count_raw": "1 (هو الجزء 9 من كتاب شرح أصول اعتقاد أهل السنة والجماعة)",
      "edition_raw": "الثامنة، 1423 هـ / 2003 م",
      "author_short": "اللالكائي",
      "metadata_volume_count": 1
    }
  },
  "quality_issues": [],
  "processing_time_ms": 8.1,
  "error": null
}