{
  "source_name": "مسألة في إعادة الإمام الصلاة دون من صلى وراءه في الجماعة - ضمن «آثار المعلمي».htm",
  "source_path_relative": "مسألة في إعادة الإمام الصلاة دون من صلى وراءه في الجماعة - ضمن «آثار المعلمي».htm",
  "status": "success",
  "source_format": "shamela_html",
  "composite_hash": "cb4869c1ef4defe99c4c2a2d3519ade9c6a7b9373e4e873e9d55cec93426a102",
  "file_hashes": {
    "مسألة في إعادة الإمام الصلاة دون من صلى وراءه في الجماعة - ضمن «آثار المعلمي».htm": "0b59cf1db80d19a91425840ce1cc31670d62823eb400081c9e921f974ab69f33"
  },
  "extracted_metadata": {
    "is_multi_volume": false,
    "volume_count": 1,
    "has_muqaddima": false,
    "display_title": "مسألة في إعادة الإمام الصلاة دون من صلى وراءه في الجماعة - ضمن «آثار المعلمي»",
    "author_short": "عبد الرحمن المعلمي اليماني",
    "shamela_category": "مسائل فقهية",
    "title_full": "مسألة في إعادة الإمام الصلاة دون من صلى وراءه في الجماعة",
    "_field_source_title_full": "الكتاب",
    "author_name_raw": "عبد الرحمن بن يحيى المُعَلِّمي اليماني (1313 - 1386 هـ)",
    "_field_source_author_name_raw": "المؤلف",
    "muhaqiq_name_raw": "محمد عزير شمس",
    "_field_source_muhaqiq_name_raw": "المحقق",
    "publisher": "دار عالم الفوائد للنشر والتوزيع",
    "_field_source_publisher": "الناشر",
    "edition_raw": "الأولى، 1434 هـ",
    "_field_source_edition_raw": "الطبعة",
    "preparer": "مؤسسة «عطاءات العلم»، جزاهم الله خيرا",
    "_field_source_preparer": "قدمه للشاملة",
    "shamela_publish_date": "10 شوّال 1442",
    "_field_source_shamela_publish_date": "تاريخ النشر بالشاملة",
    "author_birth_hijri": 1313,
    "author_death_hijri": 1386,
    "author_name_clean": "عبد الرحمن بن يحيى المُعَلِّمي اليماني",
    "edition_number": 1,
    "edition_year_hijri": 1434,
    "body_page_count": 6,
    "page_count": 6,
    "text_sample": "الرسالة السادسة والعشرونمسألة في إعادة الإمام الصلاةَ دون من صلَّىوراءه في الجماعة\n[كتب أحد العلماء إلى الشيخ المعلمي ما يلي:]عمدتي المحقق الشيخ عبد الرحمن المعلمي حفظه الله وطوَّل عمره، آمين.«لو بان حدث الإمام بعد الصلاة وقد صلّى بجماعةٍ لزمتْه الإعادةُ دونهم». فلم أقف على دليل هذا القول أبدًا ــ وقد طالعتُ وراجعت في محله ــ سوى تعليلات، كقولهم: نظرًا لاعتقاد المأموم تصح صلاته دون صلاة إمامه، مع أن الإمام غير مستقل بصلاته، بل هو حامل لصلاته وصلاةِ مَن خلفه. وكان القياس صحة صلاة مَن خلفه بصحة صلاته وبطلانها ببطلانها.وأيضًا أن قولهم «لا عبرة في الخطأ البيّن خطؤه» يقتضي لزوم إعادة صلاة من خلف الإمام، حيث إنه تبيَّن لهم الخطأ البيِّن خطؤه.والله يا سيدي! ما عرفتُ توجيه هذه المسألة ولا وقفتُ لها بدليل من كتاب وسنة، اللهم إلّا أن يكون إجماعًا. وأما القياس فغير قائلٍ لصحتها، بل يقتضي بطلانها على ما ظهر للحقير فحقِّقوا لنا، لا زلتم أهلًا لذلك.وأما قولي «من كتاب وسنة» فعلى ما أوردت العلماء في كتبهم من النصوص، لا نفس الكتاب والسنة.[فأجاب الشيخ بما يلي:]الحمد لله.لا يخفى عليكم أن الأصل في جميع الأعمال عدم الوجوب، فلا يجب علينا شيء إلا بدليل. وقد أُوجبت علينا الصلاة، وعلَّمنا النبي صلى الله عليه\nوآله وسلم كيفيتها، فكان الأصل أنها تصح على كل حالة، ولكن جاء الدليل باشتراط الطهارة من الحدثين والنجس ثوبًا وبدنًا ومكانًا، واشتراط ستر العورة واستقبال القبلة ونحوها، فعُلِم أنها لا تصحُّ صلاة بدون ذلك، وأنها لا تنعقد معها، وإذا عرضت في أثنائها أبطلتها، على ما فيها من تفصيل. وكان الأصل عدم شرع جماعة، فشُرِعت. وكان الأصل أن لا يتحمل الإمام عن المأموم شيئًا، وأن فائدة الصلاة إنما هي مجرد الربط، فورد أنه من أدرك الإمام راكعًا فركع معه أدرك الركعة، فعلمنا أنه تحمَّل عنه الفاتحة، وورد إلزام المأموم بقراءة الفاتحة فعلمنا أنه لا يحمل عنه إلّا في حق المسبوق.ثم الأصل أنها إذا انعقدت الصلاة لا يُبطلها إلا اختلال شرط في حقّ المصلي، فورد غيرها، كالكلام والأكل والعمل، وفيها تفصيل. وقام الدليل على أن التلبس بالعبادة الفاسدة باطل، فعلمنا أن ربط الصلاة بمن نعلم بطلانَ صلاته باطل، ولما لزم منه التلاعب لم تنعقد الصلاة، وأُلحِق به الكافر مطلقًا والمرأة وذو النجاسة الظاهرة لتقصير المقتدي، وحيث انتفى التلاع",
    "_quality_issues": [],
    "format_specific_metadata": {
      "shamela_category": "مسائل فقهية",
      "shamela_publish_date": "10 شوّال 1442",
      "edition_raw": "الأولى، 1434 هـ",
      "author_short": "عبد الرحمن المعلمي اليماني",
      "preparer": "مؤسسة «عطاءات العلم»، جزاهم الله خيرا"
    }
  },
  "quality_issues": [],
  "processing_time_ms": 2.2,
  "error": null
}