{
  "source_name": "معجم أسامي شيوخ أبي بكر الإسماعيلي",
  "source_path_relative": "معجم أسامي شيوخ أبي بكر الإسماعيلي",
  "status": "success",
  "source_format": "shamela_html",
  "composite_hash": "2e513f378f88f7bb3ec15317405827e15e7722b3a857cb787cab7aa15acde379",
  "file_hashes": {
    "001.htm": "44747745e076e757d4e3c2a13d8ec23509fd11ab0b6558bb72d9b4150c98a845",
    "002.htm": "c3629f89850baf8890b35388d81eb0b5316252139ac206ec3ee1ca24965746da",
    "003.htm": "08be18c799b7639c37f6c3636d595dfa3fcb7d617066d4e673d1c521845ddba4"
  },
  "extracted_metadata": {
    "is_multi_volume": true,
    "volume_count": 3,
    "has_muqaddima": false,
    "display_title": "معجم أسامي شيوخ أبي بكر الإسماعيلي",
    "author_short": "أبو بكر الإسماعيلي",
    "shamela_category": "التراجم والطبقات",
    "title_full": "المعجم في أسامي شيوخ أبي بكر الإسماعيلي",
    "_field_source_title_full": "الكتاب",
    "author_name_raw": "أبو بكر أحمد بن إبراهيم بن إسماعيل بن العباس بن مرداس الإسماعيلي الجرجاني (ت 371هـ)",
    "_field_source_author_name_raw": "المؤلف",
    "muhaqiq_name_raw": "د. زياد محمد منصور",
    "_field_source_muhaqiq_name_raw": "المحقق",
    "publisher": "مكتبة العلوم والحكم - المدينة المنورة",
    "_field_source_publisher": "الناشر",
    "edition_raw": "الأولى، 1410",
    "_field_source_edition_raw": "الطبعة",
    "volume_count_raw": "3",
    "_field_source_volume_count_raw": "عدد الأجزاء",
    "shamela_publish_date": "15 صفر 1433",
    "_field_source_shamela_publish_date": "تاريخ النشر بالشاملة",
    "author_death_hijri": 371,
    "author_name_clean": "أبو بكر أحمد بن إبراهيم بن إسماعيل بن العباس بن مرداس الإسماعيلي الجرجاني",
    "edition_number": 1,
    "edition_year_hijri": 1410,
    "_metadata_volume_count": 3,
    "body_page_count": 315,
    "page_count": 315,
    "text_sample": "‌‌مُقَدِّمَةُ الْمُؤَلِّفِ الْحَمْدُ لِلَّهِ حَمْدًا كَمَا يَنْبَغِي لِكَرَمِ وَجْهِهِ وَعِزِّ جَلَالِهِ، وَكَمَا يَقْتَضِيهِ تَتَابُعُ نِعَمِهِ وَأَفْضَالِهِ، وَصَلَّى اللَّهُ عَلَى نَبِيِّهِ مُحَمَّدٍ نَبِيِّ الرَّحْمَةِ وَالرِّسَالَةِ وَعَلَى آلِهِ وَسَلَّمَ كَثِيرًا. أَمَّا بَعْدُ: فَإِنِّي اسْتَخَرْتُ اللَّهَ عز وجل فِي حَصْرِ أَسَامِي شُيُوخِي الَّذِينَ سَمِعْتُ مِنْهُمْ وَكَتَبْتُ عَنْهُمْ وَقَرَأْتُ عَلَيْهِمُ الْحَدِيثَ، وَتَخْرِيجِهَا عَلَى حُرُوفِ الْمُعْجَمِ؛ لِيَسْهُلَ عَلَى الطَّالِبِ تَنَاوُلُهُ، وَلْيَرْجِعْ إِلَيْهِ فِي اسْمٍ إِنِ الْتَبَسَ أَوْ أَشْكَلَ، وَالِاقْتِصَارُ مِنْهُمْ لِكُلِّ وَاحِدٍ عَلَى حَدِيثٍ وَاحِدٍ يُسْتَغْرَبُ أَوْ يُسْتَفَادُ أَوْ يُسْتَحْسَنُ أَوْ حِكَايَةٍ، فَيَنْضَافُ إِلَي مَا أَرَدْتُهُ مِنْ ذَلِكَ جَمْعُ أَحَادِيثَ تَكُونُ فَوَائِدَ فِي نَفْسِهَا، وَأُبَيَّنُ حَالَ مَنْ ذَمَّمْتُ طَرِيقَهُ فِي الْحَدِيثِ بِظُهُورِ كَذِبِهِ فِيهِ أَوِ اتِّهَامِهِ بِهِ أَوْ خُرُوجِهِ عَنْ جُمْلَةِ أَهْلِ الْحَدِيثِ لِلْجَهْلِ بِهِ وَالذِّهَابِ عَنْهُ، فَمَنْ كَانَ عِنْدِي ظَاهِرَ الْأَمْرِ مِنْهُمْ؛ لَمْ أُخْرِجْهُ فِيمَا صَنَّفْتُ مِنْ حَدِيثِي، وَأَنْ أُثْبِتَ أَسَامِي مَنْ كَتَبْتُ عَنْهُ فِي صِغَرِي إِمْلَاءً بِخَطِّي فِي سَنَةِ ثَلَاثِ وَثَمَانِينَ وَمِائَتَيْنِ، فَأَنَا يَوْمَئِذٍ ابْنُ سِتِّ سِنِينَ، فَضَبَطْتُهُ ضَبْطَ مِثْلِي مِنْ حَيْثُ يُدْرِكُهُ الْمُتَأَمِّلُ لَهُ مِنْ خَطِّي\n، وَذَلِكَ عَلَى أَنِّي لَمْ أُخَرِّجْ مِنْ هَذِهِ الْبَابَةِ شَيْئًا فِيمَا صَنَّفْتُ مِنَ السُّنَنِ وَأَحَادِيثِ الشُّيُوخِ، وَاللَّهُ أَسْأَلُ التُّوْفِيقَ لِاسْتِتْمَامِهِ فِي خَيْرٍ وَعَافِيَةٍ، وَأَنْ يَنْفَعَنِي وَغَيْرِي بِهِ، وَافْتَتَحْتُ ذَلِكَ بِأَحْمَدَ لِيَكُونَ مُفْتَتَحُهُ بِاسْمِ النَّبِيِّ صلى الله عليه وسلم تَيَمُّنًا بِهِ، وَلِيَصِحَّ لِي بِهِ الِابْتِدَاءُ بِالْأَلِفِ مِنَ الْحُرُوفِ الْمُعْجَمَةِ، وَإِذْ كَانَ مُحَمَّدٌ وَأَحْمَدُ يَرْجِعَانِ إِلَى اسْمٍ وَاحِدٍ، فَإِنَّ اللَّهَ عز وجل قَالَ فِي بِشَارَةِ عِيسَى عليه السلام {وَمُبَشِّرًا بِرَسُولٍ يَأْتِي مِنْ بَعْدِي اسْمُهُ أَحْمَدُ} [الصف: 6]، كَمَا قَالَ {مُحَمَّدٌ رَسُولُ اللَّهِ}",
    "_quality_issues": [],
    "format_specific_metadata": {
      "shamela_category": "التراجم والطبقات",
      "shamela_publish_date": "15 صفر 1433",
      "volume_count_raw": "3",
      "edition_raw": "الأولى، 1410",
      "author_short": "أبو بكر الإسماعيلي",
      "metadata_volume_count": 3
    }
  },
  "quality_issues": [],
  "processing_time_ms": 5.9,
  "error": null
}